arthur_common/__init__.py
arthur_common/aggregations/__init__.py
arthur_common/aggregations/aggregator.py
arthur_common/aggregations/functions/README.md
arthur_common/aggregations/functions/__init__.py
arthur_common/aggregations/functions/agentic_aggregations.py
arthur_common/aggregations/functions/categorical_count.py
arthur_common/aggregations/functions/confusion_matrix.py
arthur_common/aggregations/functions/inference_count.py
arthur_common/aggregations/functions/inference_count_by_class.py
arthur_common/aggregations/functions/inference_null_count.py
arthur_common/aggregations/functions/mean_absolute_error.py
arthur_common/aggregations/functions/mean_squared_error.py
arthur_common/aggregations/functions/multiclass_confusion_matrix.py
arthur_common/aggregations/functions/multiclass_inference_count_by_class.py
arthur_common/aggregations/functions/numeric_stats.py
arthur_common/aggregations/functions/numeric_sum.py
arthur_common/aggregations/functions/py.typed
arthur_common/aggregations/functions/shield_aggregations.py
arthur_common/aggregations/py.typed
arthur_common/config/__init__.py
arthur_common/config/config.py
arthur_common/config/settings.yaml
arthur_common/models/__init__.py
arthur_common/models/common_schemas.py
arthur_common/models/connectors.py
arthur_common/models/constants.py
arthur_common/models/datasets.py
arthur_common/models/enums.py
arthur_common/models/llm_model_providers.py
arthur_common/models/metric_schemas.py
arthur_common/models/metrics.py
arthur_common/models/py.typed
arthur_common/models/request_schemas.py
arthur_common/models/response_schemas.py
arthur_common/models/schema_definitions.py
arthur_common/models/task_eval_schemas.py
arthur_common/models/task_job_specs.py
arthur_common/py.typed
arthur_common/tools/__init__.py
arthur_common/tools/aggregation_analyzer.py
arthur_common/tools/aggregation_loader.py
arthur_common/tools/duckdb_data_loader.py
arthur_common/tools/duckdb_utils.py
arthur_common/tools/functions.py
arthur_common-2.4.31.dist-info/METADATA
arthur_common-2.4.31.dist-info/WHEEL
arthur_common-2.4.31.dist-info/RECORD
