Metadata-Version: 2.3
Name: arthur-common
Version: 2.4.31
Summary: Utility code common to Arthur platform components.
License: MIT
Author: Arthur
Author-email: engineering@arthur.ai
Requires-Python: >=3.12,<4.0
Classifier: License :: OSI Approved :: MIT License
Classifier: Programming Language :: Python :: 3
Classifier: Programming Language :: Python :: 3.12
Classifier: Programming Language :: Python :: 3.13
Requires-Dist: datasketches (>=5.1.0)
Requires-Dist: duckdb (>=1.1.3)
Requires-Dist: fastapi (>=0.115.8)
Requires-Dist: fsspec (>=2024.10.0)
Requires-Dist: litellm (>=1.77.7,<2.0.0)
Requires-Dist: openinference-semantic-conventions (>=0.1.12,<0.2.0)
Requires-Dist: pandas (>=2.2.2,<3.0.0)
Requires-Dist: pydantic (>=2)
Requires-Dist: simple-settings (>=1.2.0)
Requires-Dist: types-python-dateutil (>=2.9.0)
Requires-Dist: types-requests (>=2.32.0.20241016)
Requires-Dist: typing-extensions (>=4.7.1)
